aesthetique/__init__.py
aesthetique/aesthetique.py
gimini/LICENSE.txt
gimini/__init__.py
gimini/gimei.py
gimini/name.py
gimini/data/names.yml
pyaesthetique-0.1.6.dist-info/DESCRIPTION.rst
pyaesthetique-0.1.6.dist-info/METADATA
pyaesthetique-0.1.6.dist-info/RECORD
pyaesthetique-0.1.6.dist-info/WHEEL
pyaesthetique-0.1.6.dist-info/metadata.json
pyaesthetique-0.1.6.dist-info/top_level.txt
